hydroshare_jupyter_sync/__init__.py
hydroshare_jupyter_sync/config_reader_writer.py
hydroshare_jupyter_sync/index_html.py
hydroshare_jupyter_sync/metadata_parser.py
hydroshare_jupyter_sync/resource_hydroshare_data.py
hydroshare_jupyter_sync/resource_local_data.py
hydroshare_jupyter_sync/resource_manager.py
hydroshare_jupyter_sync/server.py
hydroshare_jupyter_sync/assets/CUAHSI-logo-small.png
hydroshare_jupyter_sync/assets/HydroShare-logo.png
hydroshare_jupyter_sync/assets/JupyterHub-logo.png
hydroshare_jupyter_sync/assets/bundle-dev.js
hydroshare_jupyter_sync/assets/bundle-dist.js
hydroshare_jupyter_sync/assets/favicon.ico
hydroshare_jupyter_sync-0.1.10.dist-info/METADATA
hydroshare_jupyter_sync-0.1.10.dist-info/WHEEL
hydroshare_jupyter_sync-0.1.10.dist-info/top_level.txt
hydroshare_jupyter_sync-0.1.10.dist-info/RECORD
